README.md
setup.cfg
setup.py
atron_cli/__init__.py
atron_cli/atron.py
atron_cli/board.py
atron_cli/minifier.py
atron_cli.egg-info/PKG-INFO
atron_cli.egg-info/SOURCES.txt
atron_cli.egg-info/dependency_links.txt
atron_cli.egg-info/entry_points.txt
atron_cli.egg-info/requires.txt
atron_cli.egg-info/top_level.txt