Metadata-Version: 1.1
Name: atron-cli
Version: 0.0.1
Summary: A tool to intract with your MicroPython board.
Home-page: https://github.com/atron-cc/atron-cli
Author: Ahmadreza Zibaei
Author-email: zibaeiahmadreza@gmail.com
License: MIT
Keywords: micropython,hardware,circuitpython
Platform: UNKNOWN
Classifier: Topic :: Utilities
Classifier: Intended Audience :: Developers
Classifier: License :: OSI Approved :: MIT License
Classifier: Programming Language :: Python :: 2
Classifier: Programming Language :: Python :: 2.6
Classifier: Programming Language :: Python :: 2.7
Classifier: Programming Language :: Python :: 3
Classifier: Programming Language :: Python :: 3.3
Classifier: Programming Language :: Python :: 3.4
Classifier: Programming Language :: Python :: 3.5
